gbmapi/__init__.py
gbmapi/__version__.py
gbmapi/api.py
gbmapi/auth.py
gbmapi/base.py
gbmapi/exceptions.py
gbmapi/homebroker_api.py
gbmapi/utils.py
gbmapi-0.0.1.dist-info/LICENSE
gbmapi-0.0.1.dist-info/METADATA
gbmapi-0.0.1.dist-info/WHEEL
gbmapi-0.0.1.dist-info/top_level.txt
gbmapi-0.0.1.dist-info/RECORD
