Metadata-Version: 2.1
Name: gbmapi
Version: 0.0.1
Summary: GMB Non-official API for Python
Home-page: https://github.com/SAT-CFDI/python-gbm
Author: satcfdi@outlook.com
Author-email: satcfdi@outlook.com
License: MIT License
Project-URL: Documentation, https://gbmapi.readthedocs.io
Project-URL: Source, https://github.com/SAT-CFDI/python-gbm
Keywords: gbm
Classifier: Development Status :: 5 - Production/Stable
Classifier: Intended Audience :: Developers
Classifier: License :: OSI Approved :: MIT License
Classifier: Natural Language :: Spanish
Classifier: Operating System :: OS Independent
Classifier: Programming Language :: Python :: 3.11
Classifier: Programming Language :: Python :: 3.12
Requires-Python: >=3.11
License-File: LICENSE
Requires-Dist: requests
Requires-Dist: pyotp
Provides-Extra: test
Requires-Dist: coverage ; extra == 'test'
Requires-Dist: pytest ; extra == 'test'
